chains/__init__.py
chains/links/__init__.py
chains/links/dns_meta.py
chains/links/flows.py
chains/links/http_meta.py
chains/links/link.py
chains/links/packet_meta.py
chains/links/packet_tags.py
chains/links/reverse_dns.py
chains/links/tls_meta.py
chains/links/transport_meta.py
chains/sinks/__init__.py
chains/sinks/packet_printer.py
chains/sinks/packet_summary.py
chains/sinks/sink.py
chains/sources/__init__.py
chains/sources/packet_streamer.py
chains/sources/source.py
chains/utils/__init__.py
chains/utils/cache.py
chains/utils/compat.py
chains/utils/data_utils.py
chains/utils/file_utils.py
chains/utils/flow_utils.py
chains/utils/log_utils.py
chains/utils/net_utils.py
chains/utils/signal_utils.py
chains-0.2.0.data/scripts/netwatch
chains-0.2.0.data/scripts/urlwatch
chains-0.2.0.data/scripts/weird_dns
chains-0.2.0.dist-info/DESCRIPTION.rst
chains-0.2.0.dist-info/METADATA
chains-0.2.0.dist-info/RECORD
chains-0.2.0.dist-info/WHEEL
chains-0.2.0.dist-info/metadata.json
chains-0.2.0.dist-info/top_level.txt
